echidna/__init__.py
echidna/plot/__init__.py
echidna/plot/post.py
echidna/plot/ppc.py
echidna/plot/utils.py
echidna/tools/__init__.py
echidna/tools/custom_dist.py
echidna/tools/data.py
echidna/tools/eval.py
echidna/tools/housekeeping.py
echidna/tools/infer_gd.py
echidna/tools/model.py
echidna/tools/train.py
echidna/tools/utils.py
echidna/utils.py
scechidna-1.0.0.dist-info/METADATA
scechidna-1.0.0.dist-info/WHEEL
scechidna-1.0.0.dist-info/RECORD
