Metadata-Version: 2.1
Name: scechidna
Version: 1.0.0
Summary: Mapping genotype to phenotype through joint probabilistic modeling of single-cell gene expression and chromosomal copy number variation.
Home-page: https://github.com/azizilab/echidna
License: MIT
Keywords: scRNA,wgs,cnv
Author: Joy Linyue Fan
Author-email: lf2684@columbia.edu
Requires-Python: >=3.10,<4.0
Classifier: License :: OSI Approved :: MIT License
Classifier: Operating System :: OS Independent
Classifier: Programming Language :: Python :: 3
Classifier: Programming Language :: Python :: 3.10
Classifier: Programming Language :: Python :: 3.11
Classifier: Programming Language :: Python :: 3.12
Classifier: Programming Language :: Python :: 3.13
Requires-Dist: graphviz
Requires-Dist: hmmlearn
Requires-Dist: leidenalg
Requires-Dist: pandas
Requires-Dist: pyro-ppl (>=1.9.1)
Requires-Dist: requests
Requires-Dist: scanpy (>=1.10)
Requires-Dist: scikit-learn
Requires-Dist: seaborn
Project-URL: Repository, https://github.com/azizilab/echidna
